bin_packer/__init__.py
bin_packer/bin.py
bin_packer/box.py
bin_packer/item.py
bin_packer/log.py
bin_packer/packer.py
bin_packer/utils.py
3d_bin_packer-0.0.5.dist-info/LICENSE
3d_bin_packer-0.0.5.dist-info/METADATA
3d_bin_packer-0.0.5.dist-info/WHEEL
3d_bin_packer-0.0.5.dist-info/top_level.txt
3d_bin_packer-0.0.5.dist-info/RECORD
